{ "pageTicket":[
  {"identifiant":1000, "description":"Japan vs CostaRica - Football World Cup - Qatar 2022",
   "stade":"Al Bayt Stadium, Al Khor, Qatar", "prix":100 ,"date":"dimanche 27 novembre 2022"},
   {"identifiant":1001, "description":"Maroc vs Belgique - Football World Cup - Qatar 2022",
   "stade":"Al-Thumama Stadium, Doha, Qatar", "prix":150 ,"date":"dimanche 27 novembre 2022"},
   {"identifiant":1002, "description":"Croatia vs Canada - Football World Cup - Qatar 2022",
   "stade":"Khalifa International Stadium, Doha, Qatar", "prix":200
    ,"date":"dimanche 27 novembre 2022"},
   {"identifiant":1003, "description":"Spain  vs Germany - Football World Cup - Qatar 2022",
   "stade":"Al-Bayt Stadium , Al khor, Qatar", "prix":100 ,"date":"dimanche 27 novembre 2022"},
   {"identifiant":1004, "description":"Cameroon vs Serbia - Football World Cup - Qatar 2022",
   "stade":"Al-Janoub Stadium , Al Wakair, Qatar", "prix":120 ,"date":"dimanche 28 novembre 2022"},
   {"identifiant":1005, "description":"SouthKoria vs ghana - Football World Cup - Qatar 2022",
   "stade":"Al-Janoub Stadium , Al Wakair, Qatar", "prix":200 ,"date":"dimanche 29 novembre 2022"},
   {"identifiant":1006, "description":"Brazil vs Switzeland - Football World Cup - Qatar 2022",
   "stade":"Stadium 974, Doha, Qatar", "prix":120 ,"date":"dimanche 28 novembre 2022"},
   {"identifiant":1007, "description":"Portugal vs Uruguay - Football World Cup - Qatar 2022",
   "stade":"Lusail Stadium, Lusail, Qatar", "prix":170 ,"date":"dimanche 28 novembre 2022"}
  ]
  }
